interface_testcases/__init__.py
interface_testcases/testcases.py
interface_testcases-0.2.3.dist-info/METADATA
interface_testcases-0.2.3.dist-info/WHEEL
interface_testcases-0.2.3.dist-info/top_level.txt
interface_testcases-0.2.3.dist-info/RECORD
