Metadata-Version: 2.1
Name: interface-testcases
Version: 0.2.3
Summary: 提供接口测试用例生成方法
Home-page: https://github.com/caiyizhang/interface_testcases
Author: Caiyizhang
Author-email: 1031282751@qq.com
License: UNKNOWN
Platform: UNKNOWN
Requires-Dist: allpairspy
